translate_content/__init__.py
translate_content/clickhouse_op.py
translate_content/main.py
hif_tool_trans_hanz-0.0.2.dist-info/METADATA
hif_tool_trans_hanz-0.0.2.dist-info/WHEEL
hif_tool_trans_hanz-0.0.2.dist-info/license.txt
hif_tool_trans_hanz-0.0.2.dist-info/top_level.txt
hif_tool_trans_hanz-0.0.2.dist-info/RECORD
