Metadata-Version: 2.1
Name: hif-tool-trans-hanz
Version: 0.0.2
Summary: A small example package
Home-page: https://github.com/pypa/sampleproject
Author: Eno
Author-email: 166661069@qq.com
License: UNKNOWN
Platform: UNKNOWN
Classifier: Programming Language :: Python :: 3
Classifier: License :: OSI Approved :: MIT License
Classifier: Operating System :: OS Independent
Requires-Python: >=3.6
Requires-Dist: pandas
Requires-Dist: sqlalchemy
Requires-Dist: tqdm
Requires-Dist: clickhouse-driver
Requires-Dist: clickhouse-sqlalchemy
